lazynumpy/__init__.py
lazynumpy/larray.py
lazynumpy/internals/MasterMatricesManager.py
lazynumpy/internals/__init__.py
lazynumpy/internals/evals.py
lazynumpy/util/__init__.py
lazynumpy/util/optimal_eval.py
tests/__init__.py
tests/test_larray.py
tests/test_optimal_association.py
lazynumpy-0.0.1.dist-info/LICENSE
lazynumpy-0.0.1.dist-info/METADATA
lazynumpy-0.0.1.dist-info/WHEEL
lazynumpy-0.0.1.dist-info/top_level.txt
lazynumpy-0.0.1.dist-info/RECORD
