Metadata-Version: 2.1
Name: lazynumpy
Version: 0.0.1
Summary: A wrapper around numpy that does lazy evaluations to optimize for chained matrix multiplication
Home-page: https://github.com/kennethgoodman/lazynumpy
Author: Kenneth S Goodman
Author-email: kennethsgoodman@yahoo.com
License: UNKNOWN
Platform: UNKNOWN
Classifier: Programming Language :: Python :: 3
Classifier: License :: OSI Approved :: MIT License
Classifier: Operating System :: OS Independent
